<?xml version="1.0"?>
<levels>

    <category name="World 1 - Redwood Gorge">
        <level file="1-29" name="World 1-Remake" />
        <level file="1-1" name="World 1-1" />
        <level file="1-2" name="World 1-2" />
        <level file="1-3" name="World 1-3" />
        <level file="1-14" name="World 1-Airship" />
        <level file="1-24" name="World 1-Cannon" />
        <level file="1-4" name="World 1-4" />
        <level file="1-5" name="World 1-5" />
        <level file="1-8" name="World 1-A" />
        <level file="1-16" name="World 1-Castle" />
        <level file="1-19" name="Power-Up Toad House 1" />
        <level file="1-20" name="Power-Up Toad House 2" />
        <level file="1-18" name="1-UP Toad House 1" />
        <level file="1-21" name="1-UP Toad House 2" />
        <category name="Placeholders">
            <level file="1-6" name="World 1-6 Placeholder" />
            <level file="1-7" name="World 1-7 Placeholder" />
            <level file="1-9" name="World 1-B Placeholder" />
            <level file="1-10" name="World 1-C Placeholder" />
            <level file="1-22" name="Toad House Placeholder 1" />
            <level file="1-23" name="Toad House Placeholder 2" />
        </category>
    </category>

    <category name="World 2 - Dune-Dry Sandland">
        <level file="2-29" name="World 2-Remake" />
        <level file="2-1" name="World 2-1" />
        <level file="2-2" name="World 2-2" />
        <level file="2-3" name="World 2-3" />
        <level file="2-8" name="World 2-A" />
        <level file="2-14" name="World 2-Airship" />
        <level file="2-12" name="World 2-Challenge House" />
        <level file="2-4" name="World 2-4" />
        <level file="2-5" name="World 2-5" />
        <level file="2-9" name="World 2-B" />
        <level file="2-16" name="World 2-Castle" />
        <level file="2-18" name="Power-Up Toad House 1" />
        <level file="2-20" name="Power-Up Toad House 2" />
        <level file="2-19" name="1-UP Toad House" />
        <level file="2-21" name="Star Toad House" />
        <category name="Placeholders">
            <level file="2-6" name="World 2-6 Placeholder" />
            <level file="2-7" name="World 2-7 Placeholder" />
            <level file="2-10" name="World 2-C Placeholder" />
            <level file="2-24" name="World 2-Cannon Placeholder" />
            <level file="2-22" name="Toad House Placeholder 1" />
            <level file="2-23" name="Toad House Placeholder 2" />
        </category>
    </category>

    <category name="World A - Violet Rock Island">
        <level file="7-29" name="World A-Remake" />
        <level file="7-1" name="World A-1" />
        <level file="7-2" name="World A-2" />
        <level file="7-12" name="World A-Challenge House" />
        <level file="7-8" name="World A-A" />
        <level file="7-3" name="World A-3" />
        <level file="7-24" name="World A-Cannon" />
        <level file="7-9" name="World A-B" />
        <level file="7-16" name="World A-Castle" />
        <level file="7-19" name="Power-Up Toad House" />
        <level file="7-18" name="1-UP Toad House" />
        <level file="7-20" name="Star Toad House" />
        <category name="Placeholders">
            <level file="7-6" name="World A-6 Placeholder" />
            <level file="7-7" name="World A-7 Placeholder" />
            <level file="7-10" name="World A-C Placeholder" />
            <level file="7-14" name="World A-Airship Placeholder" />
            <level file="7-21" name="Toad House Placeholder 1" />
            <level file="7-22" name="Toad House Placeholder 2" />
            <level file="7-23" name="Toad House Placeholder 3" />
        </category>
    </category>

    <category name="World 3 - Ghastly Green Jungle">
        <level file="3-29" name="World 3-Remake" />
        <level file="3-1" name="World 3-1" />
        <level file="3-2" name="World 3-2" />
        <level file="3-3" name="World 3-3" />
        <level file="3-8" name="World 3-A" />
        <level file="3-14" name="World 3-Airship" />
        <level file="3-24" name="World 3-Cannon" />
        <level file="3-4" name="World 3-4" />
        <level file="3-12" name="World 3-Challenge House" />
        <level file="3-5" name="World 3-5" />
        <level file="3-9" name="World 3-B" />
        <level file="3-16" name="World 3-Castle" />
        <level file="3-18" name="Power-Up Toad House 1" />
        <level file="3-19" name="Power-Up Toad House 2" />
        <level file="3-20" name="Star Toad House 1" />
        <level file="3-21" name="Star Toad House 2" />
        <category name="Placeholders">
            <level file="3-6" name="World 3-6 Placeholder" />
            <level file="3-7" name="World 3-7 Placeholder" />
            <level file="3-10" name="World 3-C Placeholder" />
            <level file="3-22" name="Toad House Placeholder 1" />
            <level file="3-23" name="Toad House Placeholder 2" />
        </category>
    </category>

    <category name="World 4 - Cosy Chilly Hilltops">
        <level file="4-29" name="World 4-Remake" />
        <level file="4-1" name="World 4-1" />
        <level file="4-12" name="World 4-Challenge House" />
        <level file="4-2" name="World 4-2" />
        <level file="4-8" name="World 4-A" />
        <level file="4-14" name="World 4-Airship" />
        <level file="4-3" name="World 4-3" />
        <level file="4-4" name="World 4-4" />
        <level file="4-10" name="World 4-C" />
        <level file="4-5" name="World 4-5" />
        <level file="4-9" name="World 4-B" />
        <level file="4-16" name="World 4-Castle" />
        <level file="4-18" name="1-UP Toad House 1" />
        <level file="4-20" name="1-UP Toad House 2" />
        <level file="4-19" name="Power-Up Toad House 1" />
        <level file="4-22" name="Power-Up Toad House 2" />
        <level file="4-21" name="Star Toad House" />
        <category name="Placeholders">
            <level file="4-24" name="World 4-Cannon Placeholder" />
            <level file="4-6" name="World 4-6 Placeholder" />
            <level file="4-7" name="World 4-7 Placeholder" />
            <level file="4-23" name="Toad House Placeholder" />
        </category>
    </category>

    <category name="World B - Crumbleberg Ruins">
        <level file="8-29" name="World B-Remake" />
        <level file="8-1" name="World B-1" />
        <level file="8-8" name="World B-A" />
        <level file="8-24" name="World B-Cannon" />
        <level file="8-12" name="World B-Challenge House" />
        <level file="8-2" name="World B-2" />
        <level file="8-3" name="World B-3" />
        <level file="8-9" name="World B-B" />
        <level file="8-16" name="World B-Castle" />
        <level file="8-18" name="Power-Up Toad House 1" />
        <level file="8-19" name="Power-Up Toad House 2" />
        <level file="8-20" name="1-UP Toad House" />
        <category name="Placeholders">
            <level file="8-5" name="World B-5 Placeholder" />
            <level file="8-6" name="World B-6 Placeholder" />
            <level file="8-7" name="World B-7 Placeholder" />
            <level file="8-10" name="World B-C Placeholder" />
            <level file="8-14" name="World B-Airship Placeholder" />
            <level file="8-21" name="Toad House Placeholder 1" />
            <level file="8-22" name="Toad House Placeholder 2" />
            <level file="8-23" name="Toad House Placeholder 3" />
        </category>
    </category>

    <category name="World 5 - Sweet Caketop Heights">
        <level file="5-29" name="World 5-Remake" />
        <level file="5-1" name="World 5-1" />
        <level file="5-2" name="World 5-2" />
        <level file="5-12" name="World 5-Challenge House" />
        <level file="5-3" name="World 5-3" />
        <level file="5-14" name="World 5-Airship" />
        <level file="5-4" name="World 5-4" />
        <level file="5-8" name="World 5-A" />
        <level file="5-5" name="World 5-5" />
        <level file="5-6" name="World 5-6" />
        <level file="5-16" name="World 5-Castle" />
        <level file="5-18" name="Power-Up Toad House 1" />
        <level file="5-19" name="Power-Up Toad House 2" />
        <level file="5-20" name="1-UP Toad House 1" />
        <level file="5-21" name="1-UP Toad House 2" />
        <category name="Placeholders">
            <level file="5-7" name="World 5-7 Placeholder" />
            <level file="5-10" name="World 5-C Placeholder" />
            <level file="5-24" name="World 5-Cannon Placeholder" />
            <level file="5-23" name="Toad House Placeholder" />
        </category>
    </category>

    <category name="World 6 - Lava-Split Ashlands">
        <level file="6-29" name="World 6-Remake" />
        <level file="6-1" name="World 6-1" />
        <level file="6-12" name="World 6-Challenge House" />
        <level file="6-2" name="World 6-2" />
        <level file="6-9" name="World 6-B" />
        <level file="6-3" name="World 6-3" />
        <level file="6-8" name="World 6-A" />
        <level file="6-14" name="World 6-Airship" />
        <level file="6-4" name="World 6-4" />
        <level file="6-5" name="World 6-5" />
        <level file="6-16" name="World 6-Castle" />
        <level file="6-18" name="Power-Up Toad House" />
        <level file="6-20" name="1-UP Toad House 1" />
        <level file="6-21" name="1-UP Toad House 2" />
        <level file="6-19" name="Star Toad House" />
        <category name="Placeholders">
            <level file="6-6" name="World 6-6 Placeholder" />
            <level file="6-7" name="World 6-7 Placeholder" />
            <level file="6-24" name="World 6-Cannon Placeholder" />
            <level file="6-22" name="Toad House Placeholder 1" />
            <level file="6-23" name="Toad House Placeholder 2" />
            </category>
    </category>

    <category name="World S - Rainbow Road">
        <level file="9-29" name="World S-Remake" />
        <level file="9-1" name="World S-1" />
        <level file="9-2" name="World S-2" />
        <level file="9-3" name="World S-3" />
        <level file="9-4" name="World S-4" />
        <level file="9-5" name="World S-5" />
        <level file="9-6" name="World S-6" />
        <level file="9-7" name="World S-7" />
        <level file="9-16" name="World S-Castle" />
        <level file="9-18" name="Star Toad House" />
    </category>

    <category name="Other">
        <level file="6-27" name="Credits" />
    </category>

    <category name="Extra Stage Packs">

        <category name="Steam Gardens Pack">
            <level file="dlc/10-1" name="Course 1" />
            <level file="dlc/10-2" name="Course 2" />
            <level file="dlc/10-3" name="Course 3" />
        </category>

        <category name="Coin Challenge Pack A">
            <level file="dlc/11-1" name="Course 1" />
            <level file="dlc/11-2" name="Course 2" />
            <level file="dlc/11-3" name="Course 3" />
        </category>

        <category name="Night Sancturary Pack">
            <level file="dlc/12-1" name="Course 1" />
            <level file="dlc/12-2" name="Course 2" />
            <level file="dlc/12-3" name="Course 3" />
        </category>

        <category name="Gold Mushroom Pack">
            <level file="dlc/13-1" name="Course 1" />
            <level file="dlc/13-2" name="Course 2" />
            <level file="dlc/13-3" name="Course 3" />
        </category>

        <category name="NSMB Remix Pack ">
            <level file="dlc/14-1" name="Course 1" />
            <level file="dlc/14-2" name="Course 2" />
            <level file="dlc/14-3" name="Course 3" />
        </category>

        <category name="Frosty Pack">
            <level file="dlc/15-1" name="Course 1" />
            <level file="dlc/15-2" name="Course 2" />
            <level file="dlc/15-3" name="Course 3" />
        </category>

        <category name="Bowser's Domain Pack">
            <level file="dlc/16-1" name="Course 1" />
            <level file="dlc/16-2" name="Course 2" />
            <level file="dlc/16-3" name="Course 3" />
        </category>

        <category name="Beach Pack">
            <level file="dlc/17-1" name="Course 1" />
            <level file="dlc/17-2" name="Course 2" />
            <level file="dlc/17-3" name="Course 3" />
        </category>

        <category name="Space Pack">
            <level file="dlc/18-1" name="Course 1" />
            <level file="dlc/18-2" name="Course 2" />
            <level file="dlc/18-3" name="Course 3" />
        </category>

        <category name="Impossible Pack">
            <level file="dlc/19-1" name="Course 1" />
            <level file="dlc/19-2" name="Course 2" />
            <level file="dlc/19-3" name="Course 3" />
        </category>

    </category>

  <category name="SMBNext Extras">
           <level file="Beta1-2" name="World 1-2 Beta" />
           <level file="Beta1-Tower-One" name="World 1-Tower Beta 1" />
           <level file="Beta1-Tower-Two" name="World 1-Tower Beta 2" />
		<level file="Beta2-4" name="World 2-4 Unused" />
		<level file="BetaA-Castle" name="World A-Castle (Unused)" />

  </category>
  
  <category name="World 1 - Redwood Gorge (Hard Mode)">
        <level file="hard/1-1" name="World 1-1 (Hard Mode)" />
        <level file="hard/1-2" name="World 1-2 (Hard Mode)" />
        <level file="hard/1-3" name="World 1-3 (Hard Mode)" />
        <level file="hard/1-14" name="World 1-Airship (Hard Mode)" />
        <level file="hard/1-4" name="World 1-4 (Hard Mode)" />
        <level file="hard/1-5" name="World 1-5 (Hard Mode)" />
        <level file="hard/1-8" name="World 1-A (Hard Mode)" />
        <level file="hard/1-16" name="World 1-Castle (Hard Mode)" />
  </category>
  
  <category name="World 2 - Dune-Dry Sandland (Hard Mode)">
        <level file="hard/2-1" name="World 2-1 (Hard Mode)" />
        <level file="hard/2-2" name="World 2-2 (Hard Mode)" />
        <level file="hard/2-3" name="World 2-3 (Hard Mode)" />
        <level file="hard/2-8" name="World 2-A (Hard Mode)" />
        <level file="hard/2-14" name="World 2-Airship (Hard Mode)" />
        <level file="hard/2-4" name="World 2-4 (Hard Mode)" />
        <level file="hard/2-5" name="World 2-5 (Hard Mode)" />
        <level file="hard/2-9" name="World 2-B (Hard Mode)" />
        <level file="hard/2-16" name="World 2-Castle (Hard Mode)" />
    </category>
	
	<category name="World A - Violet Rock Island (Hard Mode)">
        <level file="hard/7-1" name="World A-1 (Hard Mode)" />
        <level file="hard/7-2" name="World A-2 (Hard Mode)" />
        <level file="hard/7-8" name="World A-A (Hard Mode)" />
        <level file="hard/7-3" name="World A-3 (Hard Mode)" />
        <level file="hard/7-9" name="World A-B (Hard Mode)" />
        <level file="hard/7-16" name="World A-Castle (Hard Mode)" />
    </category>
	
	<category name="World 3 - Ghastly Green Jungle (Hard Mode)">
        <level file="hard/3-1" name="World 3-1 (Hard Mode)" />
        <level file="hard/3-2" name="World 3-2 (Hard Mode)" />
        <level file="hard/3-3" name="World 3-3 (Hard Mode)" />
        <level file="hard/3-8" name="World 3-A (Hard Mode)" />
        <level file="hard/3-14" name="World 3-Airship (Hard Mode)" />
        <level file="hard/3-4" name="World 3-4 (Hard Mode)" />
        <level file="hard/3-5" name="World 3-5 (Hard Mode)" />
        <level file="hard/3-9" name="World 3-B (Hard Mode)" />
        <level file="hard/3-16" name="World 3-Castle (Hard Mode)" />
    </category>
	
	<category name="World 4 - Cosy Chilly Hilltops (Hard Mode)">
        <level file="hard/4-1" name="World 4-1 (Hard Mode)" />
        <level file="hard/4-2" name="World 4-2 (Hard Mode)" />
        <level file="hard/4-8" name="World 4-A (Hard Mode)" />
        <level file="hard/4-14" name="World 4-Airship (Hard Mode)" />
        <level file="hard/4-3" name="World 4-3 (Hard Mode)" />
        <level file="hard/4-4" name="World 4-4 (Hard Mode)" />
        <level file="hard/4-10" name="World 4-C (Hard Mode)" />
        <level file="hard/4-5" name="World 4-5 (Hard Mode)" />
        <level file="hard/4-9" name="World 4-B (Hard Mode)" />
        <level file="hard/4-16" name="World 4-Castle (Hard Mode)" />
    </category>
	
	<category name="World B - Crumbleberg Ruins (Hard Mode)">
        <level file="hard/8-1" name="World B-1 (Hard Mode)" />
        <level file="hard/8-8" name="World B-A (Hard Mode)" />
        <level file="hard/8-2" name="World B-2 (Hard Mode)" />
        <level file="hard/8-3" name="World B-3 (Hard Mode)" />
        <level file="hard/8-9" name="World B-B (Hard Mode)" />
        <level file="hard/8-16" name="World B-Castle (Hard Mode)" />
    </category>
	
	<category name="World 5 - Sweet Caketop Heights (Hard Mode)">
        <level file="hard/5-1" name="World 5-1 (Hard Mode)" />
        <level file="hard/5-2" name="World 5-2 (Hard Mode)" />
        <level file="hard/5-3" name="World 5-3 (Hard Mode)" />
        <level file="hard/5-14" name="World 5-Airship (Hard Mode)" />
        <level file="hard/5-4" name="World 5-4 (Hard Mode)" />
        <level file="hard/5-8" name="World 5-A (Hard Mode)" />
        <level file="hard/5-5" name="World 5-5 (Hard Mode)" />
        <level file="hard/5-6" name="World 5-6 (Hard Mode)" />
        <level file="hard/5-16" name="World 5-Castle (Hard Mode)" />
    </category>
	
	<category name="World 6 - Lava-Split Ashlands Hard Mode)">
        <level file="hard/6-1" name="World 6-1 (Hard Mode)" />
        <level file="hard/6-2" name="World 6-2 (Hard Mode)" />
        <level file="hard/6-9" name="World 6-B (Hard Mode)" />
        <level file="hard/6-3" name="World 6-3 (Hard Mode)" />
        <level file="hard/6-8" name="World 6-A (Hard Mode)" />
        <level file="hard/6-14" name="World 6-Airship (Hard Mode)" />
        <level file="hard/6-4" name="World 6-4 (Hard Mode)" />
        <level file="hard/6-5" name="World 6-5 (Hard Mode)" />
        <level file="hard/6-16" name="World 6-Castle (Hard Mode)" />
    </category>
	
	<category name="World S - Rainbow Road (Hard Mode)">
        <level file="hard/9-1" name="World S-1 (Hard Mode)" />
        <level file="hard/9-2" name="World S-2 (Hard Mode)" />
        <level file="hard/9-3" name="World S-3 (Hard Mode)" />
        <level file="hard/9-4" name="World S-4 (Hard Mode)" />
        <level file="hard/9-5" name="World S-5 (Hard Mode)" />
        <level file="hard/9-6" name="World S-6 (Hard Mode)" />
        <level file="hard/9-7" name="World S-7 (Hard Mode)" />
        <level file="hard/9-16" name="World S-Castle (Hard Mode)" />
    </category>
	
</levels>
